{
  "consejero": [
    {
      "id": "1",
      "username": "ADMIN",
      "pass": "NjY2OTExMzk=",
      "rut": "20492799-5",
      "nroDocumento": "123456789",
      "rol": "consejero"
    }
  ],
  "user": [
    {
      "id": 1733875105464,
      "username": "shang",
      "pass": "aG9sYW11bmRv",
      "rut": "20.492.799.5",
      "nroDocumento": "123.456.789"
    }
  ],
  "arqs": [],
  "cali": [],
  "Est": [],
  "Eti": [],
  "Ing": [],
  "Port": [],
  "Movil": [],
  "arqsAd": [],
  "caliAd": [],
  "EstAd": [],
  "EtiAd": [],
  "IngAd": [],
  "PortAd": [],
  "MovilAd": [],
  "Meet": [],
  "Notas": []
}